libname/__init__.py
libname/scrapepi.py
scrapepi-0.0.1.dist-info/METADATA
scrapepi-0.0.1.dist-info/WHEEL
scrapepi-0.0.1.dist-info/top_level.txt
scrapepi-0.0.1.dist-info/RECORD
